{
  "asset": "GOLD_CFD",
  "generated_utc": "2025-12-19T13:25:01.973234+00:00",
  "total_samples": 2725,
  "baseline_window": 500,
  "recent_window": 120,
  "features": {
    "p_score": {
      "recent_mean": 28.0375,
      "recent_std": 13.277198891960106,
      "recent_min": 0.0,
      "recent_max": 50.0,
      "baseline_mean": 20.31682304410401,
      "baseline_std": 18.27008799086791,
      "psi": 0.6292770305004476,
      "drift_flag": true
    },
    "rel_atr": {
      "recent_mean": 0.0006334295590255124,
      "recent_std": 0.00034117637830944513,
      "recent_min": 0.0001110607410076,
      "recent_max": 0.0020087404403237,
      "baseline_mean": 0.000601687961570662,
      "baseline_std": 0.00045806957355591193,
      "psi": 1.1474422217756675,
      "drift_flag": true
    },
    "ema21_slope": {
      "recent_mean": 0.0007344945201457769,
      "recent_std": 0.0014623102447491828,
      "recent_min": -0.0012013429710951,
      "recent_max": 0.0036535098394738,
      "baseline_mean": 0.00253688985614167,
      "baseline_std": 0.003513794088786286,
      "psi": 5.280063666572661,
      "drift_flag": true
    },
    "bias_long": {
      "recent_mean": 0.9083333333333333,
      "recent_std": 0.28855482821967976,
      "recent_min": 0.0,
      "recent_max": 1.0,
      "baseline_mean": 0.748,
      "baseline_std": 0.43416126036301306,
      "psi": null,
      "drift_flag": false
    },
    "bias_short": {
      "recent_mean": 0.09166666666666666,
      "recent_std": 0.28855482821967976,
      "recent_min": 0.0,
      "recent_max": 1.0,
      "baseline_mean": 0.16,
      "baseline_std": 0.36660605559646714,
      "psi": null,
      "drift_flag": false
    },
    "momentum_vol_ratio": {
      "recent_mean": 0.0,
      "recent_std": 0.0,
      "recent_min": 0.0,
      "recent_max": 0.0,
      "baseline_mean": 0.0,
      "baseline_std": 0.0,
      "psi": null,
      "drift_flag": false
    },
    "order_flow_imbalance": {
      "recent_mean": 0.0,
      "recent_std": 0.0,
      "recent_min": 0.0,
      "recent_max": 0.0,
      "baseline_mean": 0.0,
      "baseline_std": 0.0,
      "psi": null,
      "drift_flag": false
    },
    "order_flow_pressure": {
      "recent_mean": 0.0,
      "recent_std": 0.0,
      "recent_min": 0.0,
      "recent_max": 0.0,
      "baseline_mean": 0.0,
      "baseline_std": 0.0,
      "psi": null,
      "drift_flag": false
    },
    "order_flow_aggressor": {
      "recent_mean": 0.0,
      "recent_std": 0.0,
      "recent_min": 0.0,
      "recent_max": 0.0,
      "baseline_mean": 0.0,
      "baseline_std": 0.0,
      "psi": null,
      "drift_flag": false
    },
    "news_sentiment": {
      "recent_mean": 0.0,
      "recent_std": 0.0,
      "recent_min": 0.0,
      "recent_max": 0.0,
      "baseline_mean": 0.0,
      "baseline_std": 0.0,
      "psi": null,
      "drift_flag": false
    },
    "news_event_severity": {
      "recent_mean": 0.0,
      "recent_std": 0.0,
      "recent_min": 0.0,
      "recent_max": 0.0,
      "baseline_mean": 0.0,
      "baseline_std": 0.0,
      "psi": null,
      "drift_flag": false
    },
    "realtime_confidence": {
      "recent_mean": 0.9773400163548641,
      "recent_std": 0.05084873382881,
      "recent_min": 0.7023242777894518,
      "recent_max": 1.0,
      "baseline_mean": 0.976379155924863,
      "baseline_std": 0.04809447166900689,
      "psi": 0.06368842645874216,
      "drift_flag": false
    },
    "volatility_ratio": {
      "recent_mean": 0.0,
      "recent_std": 0.0,
      "recent_min": 0.0,
      "recent_max": 0.0,
      "baseline_mean": 0.0,
      "baseline_std": 0.0,
      "psi": null,
      "drift_flag": false
    },
    "volatility_regime_flag": {
      "recent_mean": 0.0,
      "recent_std": 0.0,
      "recent_min": 0.0,
      "recent_max": 0.0,
      "baseline_mean": 0.0,
      "baseline_std": 0.0,
      "psi": null,
      "drift_flag": false
    },
    "precision_score": {
      "recent_mean": 55.31666666666667,
      "recent_std": 17.82413314083527,
      "recent_min": 0.0,
      "recent_max": 62.0,
      "baseline_mean": 55.196,
      "baseline_std": 17.842465748881235,
      "psi": 1.3322692928400866e-06,
      "drift_flag": false
    },
    "precision_trigger_ready": {
      "recent_mean": 0.725,
      "recent_std": 0.44651427748729383,
      "recent_min": 0.0,
      "recent_max": 1.0,
      "baseline_mean": 0.736,
      "baseline_std": 0.44079927404658914,
      "psi": null,
      "drift_flag": false
    },
    "precision_trigger_arming": {
      "recent_mean": 0.3,
      "recent_std": 0.45825756949558394,
      "recent_min": 0.0,
      "recent_max": 1.0,
      "baseline_mean": 0.362,
      "baseline_std": 0.48057881767718397,
      "psi": null,
      "drift_flag": false
    },
    "precision_trigger_fire": {
      "recent_mean": 0.425,
      "recent_std": 0.4943429983321297,
      "recent_min": 0.0,
      "recent_max": 1.0,
      "baseline_mean": 0.374,
      "baseline_std": 0.4838636171484688,
      "psi": null,
      "drift_flag": false
    },
    "precision_trigger_confidence": {
      "recent_mean": 0.44024166666666675,
      "recent_std": 0.1615943478711087,
      "recent_min": 0.0,
      "recent_max": 0.54,
      "baseline_mean": 0.441124,
      "baseline_std": 0.1566926821009839,
      "psi": 0.022281060556551994,
      "drift_flag": false
    },
    "precision_order_flow_ready": {
      "recent_mean": 0.0,
      "recent_std": 0.0,
      "recent_min": 0.0,
      "recent_max": 0.0,
      "baseline_mean": 0.0,
      "baseline_std": 0.0,
      "psi": null,
      "drift_flag": false
    },
    "structure_flip_flag": {
      "recent_mean": 0.6166666666666667,
      "recent_std": 0.486198404860494,
      "recent_min": 0.0,
      "recent_max": 1.0,
      "baseline_mean": 0.54,
      "baseline_std": 0.49839743177508444,
      "psi": null,
      "drift_flag": false
    },
    "momentum_trail_activation_rr": {
      "recent_mean": 0.0,
      "recent_std": 0.0,
      "recent_min": 0.0,
      "recent_max": 0.0,
      "baseline_mean": 0.0,
      "baseline_std": 0.0,
      "psi": null,
      "drift_flag": false
    },
    "momentum_trail_lock_ratio": {
      "recent_mean": 0.0,
      "recent_std": 0.0,
      "recent_min": 0.0,
      "recent_max": 0.0,
      "baseline_mean": 0.0,
      "baseline_std": 0.0,
      "psi": null,
      "drift_flag": false
    },
    "momentum_trail_price": {
      "recent_mean": 0.0,
      "recent_std": 0.0,
      "recent_min": 0.0,
      "recent_max": 0.0,
      "baseline_mean": 0.0,
      "baseline_std": 0.0,
      "psi": null,
      "drift_flag": false
    }
  },
  "alerts": [
    {
      "feature": "p_score",
      "psi": 0.6292770305004476,
      "severity": "critical"
    },
    {
      "feature": "rel_atr",
      "psi": 1.1474422217756675,
      "severity": "critical"
    },
    {
      "feature": "ema21_slope",
      "psi": 5.280063666572661,
      "severity": "critical"
    }
  ],
  "latest_snapshot": {
    "p_score": 0,
    "rel_atr": 0.000671741180750791,
    "ema21_slope": -0.0007619173158845413,
    "bias_long": 0.0,
    "bias_short": 1.0,
    "momentum_vol_ratio": 0.0,
    "order_flow_status": "ok",
    "order_flow_imbalance": null,
    "order_flow_pressure": 0.0,
    "order_flow_aggressor": null,
    "news_sentiment": 0.0,
    "news_event_severity": 0.0,
    "realtime_confidence": 1.0,
    "volatility_ratio": 0.0,
    "volatility_regime_flag": 0.0,
    "precision_score": 62.0,
    "precision_trigger_ready": 1.0,
    "precision_trigger_arming": 0.0,
    "precision_trigger_fire": 1.0,
    "precision_trigger_confidence": 0.54,
    "precision_order_flow_ready": 0.0,
    "momentum_trail_activation_rr": 0.0,
    "momentum_trail_lock_ratio": 0.0,
    "momentum_trail_price": 0.0,
    "structure_flip_flag": 0.0
  }
}