{
  "asset": "BTCUSD",
  "generated_utc": "2026-03-26T14:16:37Z",
  "crypto_risk": {
    "irs": 20,
    "band": "LOW",
    "since_utc": "2026-03-26T14:16:37Z",
    "updated_utc": "2026-03-26T14:16:37Z",
    "reasons": [
      "ATR elevated 1.7×"
    ],
    "policy": [
      "increase_spread_buffer_when_volatility>=1.5×",
      "discord_alert_cooldown:10m"
    ],
    "metrics": {
      "price": 69638.79,
      "roc_30m_pct": 0.0020246926344316823,
      "roc_5m_pct": 0.10205872574074872,
      "atr5_usd": 188.4471428571404,
      "atr5_ratio": 1.664779933743471,
      "range_position_pct": 18.711158151021024,
      "session_points": 0.0,
      "comms_points": 0.0,
      "comms_from_flag": 0.0,
      "comms_from_sentiment": 0.0,
      "sentiment_score": null,
      "components": {
        "speed": 0.0,
        "volatility": 10.0,
        "range": 10.0,
        "comms": 0.0
      },
      "variance_ratio": 0.3233444367108117
    },
    "score_breakdown": {
      "speed": 0.0,
      "volatility": 10.0,
      "range": 10.0,
      "comms": 0.0
    },
    "news_flag": 0
  }
}