{
  "generated_utc": "2026-03-24T00:36:24.339777Z",
  "public_dir": "public",
  "assets": {
    "BTCUSD": {
      "timeframes": {
        "k1m": {
          "provider": "twelvedata",
          "latency_seconds": 132.977605,
          "freshness_limit_seconds": 240.0,
          "latest_utc": "2026-03-24T00:34:00+00:00",
          "retrieved_at_utc": "2026-03-24T00:36:12Z"
        },
        "k5m": {
          "provider": "twelvedata",
          "latency_seconds": 366.425223,
          "freshness_limit_seconds": 900.0,
          "latest_utc": "2026-03-24T00:30:00+00:00",
          "retrieved_at_utc": "2026-03-24T00:36:06Z"
        },
        "k1h": {
          "provider": "twelvedata",
          "latency_seconds": 2167.637818,
          "freshness_limit_seconds": 5400.0,
          "latest_utc": "2026-03-24T00:00:00+00:00",
          "retrieved_at_utc": "2026-03-24T00:36:07Z"
        },
        "k4h": {
          "provider": "twelvedata",
          "latency_seconds": 2163.287089,
          "freshness_limit_seconds": 21600.0,
          "latest_utc": "2026-03-24T00:00:00+00:00",
          "retrieved_at_utc": "2026-03-24T00:36:03Z"
        }
      }
    },
    "EURUSD": {
      "timeframes": {
        "k1m": {
          "provider": "twelvedata",
          "latency_seconds": 117.104525,
          "freshness_limit_seconds": 240.0,
          "latest_utc": "2026-03-24T00:34:00+00:00",
          "retrieved_at_utc": "2026-03-24T00:35:57Z"
        },
        "k5m": {
          "provider": "twelvedata",
          "latency_seconds": 357.079908,
          "freshness_limit_seconds": 900.0,
          "latest_utc": "2026-03-24T00:30:00+00:00",
          "retrieved_at_utc": "2026-03-24T00:35:57Z"
        },
        "k1h": {
          "provider": "twelvedata",
          "latency_seconds": 2157.164533,
          "freshness_limit_seconds": 5400.0,
          "latest_utc": "2026-03-24T00:00:00+00:00",
          "retrieved_at_utc": "2026-03-24T00:35:57Z"
        },
        "k4h": {
          "provider": "twelvedata",
          "latency_seconds": 2157.18992,
          "freshness_limit_seconds": 21600.0,
          "latest_utc": "2026-03-24T00:00:00+00:00",
          "retrieved_at_utc": "2026-03-24T00:35:57Z"
        }
      }
    },
    "GOLD_CFD": {
      "timeframes": {
        "k1m": {
          "provider": "twelvedata",
          "latency_seconds": 117.087589,
          "freshness_limit_seconds": 240.0,
          "latest_utc": "2026-03-24T00:34:00+00:00",
          "retrieved_at_utc": "2026-03-24T00:35:57Z"
        },
        "k5m": {
          "provider": "twelvedata",
          "latency_seconds": 358.80987,
          "freshness_limit_seconds": 900.0,
          "latest_utc": "2026-03-24T00:30:00+00:00",
          "retrieved_at_utc": "2026-03-24T00:35:58Z"
        },
        "k1h": {
          "provider": "twelvedata",
          "latency_seconds": 2164.421605,
          "freshness_limit_seconds": 5400.0,
          "latest_utc": "2026-03-24T00:00:00+00:00",
          "retrieved_at_utc": "2026-03-24T00:36:04Z"
        },
        "k4h": {
          "provider": "twelvedata",
          "latency_seconds": 2170.318358,
          "freshness_limit_seconds": 21600.0,
          "latest_utc": "2026-03-24T00:00:00+00:00",
          "retrieved_at_utc": "2026-03-24T00:36:10Z"
        }
      }
    },
    "NVDA": {
      "timeframes": {
        "k1m": {
          "provider": "unknown",
          "latency_seconds": null,
          "freshness_limit_seconds": 240.0,
          "latest_utc": null,
          "retrieved_at_utc": "2026-03-24T00:35:56Z"
        },
        "k5m": {
          "provider": "unknown",
          "latency_seconds": null,
          "freshness_limit_seconds": 900.0,
          "latest_utc": null,
          "retrieved_at_utc": "2026-03-24T00:35:56Z"
        },
        "k1h": {
          "provider": "unknown",
          "latency_seconds": null,
          "freshness_limit_seconds": 5400.0,
          "latest_utc": null,
          "retrieved_at_utc": "2026-03-24T00:35:56Z"
        },
        "k4h": {
          "provider": "unknown",
          "latency_seconds": null,
          "freshness_limit_seconds": 21600.0,
          "latest_utc": null,
          "retrieved_at_utc": "2026-03-24T00:35:56Z"
        }
      }
    },
    "USOIL": {
      "timeframes": {
        "k1m": {
          "provider": "twelvedata",
          "latency_seconds": 250.941243,
          "freshness_limit_seconds": 240.0,
          "latest_utc": "2026-03-24T00:32:00+00:00",
          "retrieved_at_utc": "2026-03-24T00:36:10Z"
        },
        "k5m": {
          "provider": "twelvedata",
          "latency_seconds": 362.367091,
          "freshness_limit_seconds": 900.0,
          "latest_utc": "2026-03-24T00:30:00+00:00",
          "retrieved_at_utc": "2026-03-24T00:36:02Z"
        },
        "k1h": {
          "provider": "twelvedata",
          "latency_seconds": 2165.49167,
          "freshness_limit_seconds": 5400.0,
          "latest_utc": "2026-03-24T00:00:00+00:00",
          "retrieved_at_utc": "2026-03-24T00:36:05Z"
        },
        "k4h": {
          "provider": "twelvedata",
          "latency_seconds": 2157.781906,
          "freshness_limit_seconds": 21600.0,
          "latest_utc": "2026-03-24T00:00:00+00:00",
          "retrieved_at_utc": "2026-03-24T00:35:57Z"
        }
      }
    },
    "XAGUSD": {
      "timeframes": {
        "k1m": {
          "provider": "twelvedata",
          "latency_seconds": 135.179388,
          "freshness_limit_seconds": 240.0,
          "latest_utc": "2026-03-24T00:34:00+00:00",
          "retrieved_at_utc": "2026-03-24T00:36:15Z"
        },
        "k5m": {
          "provider": "twelvedata",
          "latency_seconds": 368.618248,
          "freshness_limit_seconds": 900.0,
          "latest_utc": "2026-03-24T00:30:00+00:00",
          "retrieved_at_utc": "2026-03-24T00:36:08Z"
        },
        "k1h": {
          "provider": "twelvedata",
          "latency_seconds": 2161.110883,
          "freshness_limit_seconds": 5400.0,
          "latest_utc": "2026-03-24T00:00:00+00:00",
          "retrieved_at_utc": "2026-03-24T00:36:01Z"
        },
        "k4h": {
          "provider": "twelvedata",
          "latency_seconds": 2160.026843,
          "freshness_limit_seconds": 21600.0,
          "latest_utc": "2026-03-24T00:00:00+00:00",
          "retrieved_at_utc": "2026-03-24T00:36:00Z"
        }
      }
    }
  },
  "providers": {
    "twelvedata": {
      "count": 20,
      "latency_avg_seconds": 1209.551,
      "latency_max_seconds": 2170.318358,
      "stale_count": 1
    },
    "unknown": {
      "count": 4,
      "latency_avg_seconds": null,
      "latency_max_seconds": null,
      "stale_count": 0
    }
  }
}