{
  "generated_utc": "2026-04-19T02:36:51.662010Z",
  "public_dir": "public",
  "assets": {
    "BTCUSD": {
      "timeframes": {
        "k1m": {
          "provider": "twelvedata",
          "latency_seconds": 124.739088,
          "freshness_limit_seconds": 240.0,
          "latest_utc": "2026-04-19T02:34:00+00:00",
          "retrieved_at_utc": "2026-04-19T02:36:04Z"
        },
        "k5m": {
          "provider": "twelvedata",
          "latency_seconds": 375.133642,
          "freshness_limit_seconds": 900.0,
          "latest_utc": "2026-04-19T02:30:00+00:00",
          "retrieved_at_utc": "2026-04-19T02:36:15Z"
        },
        "k1h": {
          "provider": "twelvedata",
          "latency_seconds": 2192.793682,
          "freshness_limit_seconds": 5400.0,
          "latest_utc": "2026-04-19T02:00:00+00:00",
          "retrieved_at_utc": "2026-04-19T02:36:32Z"
        },
        "k4h": {
          "provider": "twelvedata",
          "latency_seconds": 9368.19322,
          "freshness_limit_seconds": 21600.0,
          "latest_utc": "2026-04-19T00:00:00+00:00",
          "retrieved_at_utc": "2026-04-19T02:36:08Z"
        }
      }
    },
    "EURUSD": {
      "timeframes": {
        "k1m": {
          "provider": "twelvedata",
          "latency_seconds": 129.665361,
          "freshness_limit_seconds": 240.0,
          "latest_utc": "2026-04-19T02:34:00+00:00",
          "retrieved_at_utc": "2026-04-19T02:36:09Z"
        },
        "k5m": {
          "provider": "twelvedata",
          "latency_seconds": 372.913861,
          "freshness_limit_seconds": 900.0,
          "latest_utc": "2026-04-19T02:30:00+00:00",
          "retrieved_at_utc": "2026-04-19T02:36:12Z"
        },
        "k1h": {
          "provider": "twelvedata",
          "latency_seconds": 2188.558077,
          "freshness_limit_seconds": 5400.0,
          "latest_utc": "2026-04-19T02:00:00+00:00",
          "retrieved_at_utc": "2026-04-19T02:36:28Z"
        },
        "k4h": {
          "provider": "twelvedata",
          "latency_seconds": 5765.940729,
          "freshness_limit_seconds": 21600.0,
          "latest_utc": "2026-04-19T01:00:00+00:00",
          "retrieved_at_utc": "2026-04-19T02:36:05Z"
        }
      }
    },
    "GOLD_CFD": {
      "timeframes": {
        "k1m": {
          "provider": "twelvedata",
          "latency_seconds": 84.948381,
          "freshness_limit_seconds": 240.0,
          "latest_utc": "2026-04-19T02:35:00+00:00",
          "retrieved_at_utc": "2026-04-19T02:36:24Z"
        },
        "k5m": {
          "provider": "twelvedata",
          "latency_seconds": 93.665488,
          "freshness_limit_seconds": 900.0,
          "latest_utc": "2026-04-19T02:35:00+00:00",
          "retrieved_at_utc": "2026-04-19T02:36:33Z"
        },
        "k1h": {
          "provider": "twelvedata",
          "latency_seconds": 2166.58849,
          "freshness_limit_seconds": 5400.0,
          "latest_utc": "2026-04-19T02:00:00+00:00",
          "retrieved_at_utc": "2026-04-19T02:36:06Z"
        },
        "k4h": {
          "provider": "twelvedata",
          "latency_seconds": 5779.735347,
          "freshness_limit_seconds": 21600.0,
          "latest_utc": "2026-04-19T01:00:00+00:00",
          "retrieved_at_utc": "2026-04-19T02:36:19Z"
        }
      }
    },
    "NVDA": {
      "timeframes": {
        "k1m": {
          "provider": "unknown",
          "latency_seconds": null,
          "freshness_limit_seconds": 240.0,
          "latest_utc": null,
          "retrieved_at_utc": "2026-04-19T02:36:03Z"
        },
        "k5m": {
          "provider": "unknown",
          "latency_seconds": null,
          "freshness_limit_seconds": 900.0,
          "latest_utc": null,
          "retrieved_at_utc": "2026-04-19T02:36:03Z"
        },
        "k1h": {
          "provider": "unknown",
          "latency_seconds": null,
          "freshness_limit_seconds": 5400.0,
          "latest_utc": null,
          "retrieved_at_utc": "2026-04-19T02:36:03Z"
        },
        "k4h": {
          "provider": "unknown",
          "latency_seconds": null,
          "freshness_limit_seconds": 21600.0,
          "latest_utc": null,
          "retrieved_at_utc": "2026-04-19T02:36:03Z"
        }
      }
    },
    "USOIL": {
      "timeframes": {
        "k1m": {
          "provider": "twelvedata",
          "latency_seconds": 106624.764912,
          "freshness_limit_seconds": 240.0,
          "latest_utc": "2026-04-17T20:59:00+00:00",
          "retrieved_at_utc": "2026-04-19T02:36:04Z"
        },
        "k5m": {
          "provider": "twelvedata",
          "latency_seconds": 106864.763824,
          "freshness_limit_seconds": 900.0,
          "latest_utc": "2026-04-17T20:55:00+00:00",
          "retrieved_at_utc": "2026-04-19T02:36:04Z"
        },
        "k1h": {
          "provider": "twelvedata",
          "latency_seconds": 110164.999085,
          "freshness_limit_seconds": 5400.0,
          "latest_utc": "2026-04-17T20:00:00+00:00",
          "retrieved_at_utc": "2026-04-19T02:36:04Z"
        },
        "k4h": {
          "provider": "twelvedata",
          "latency_seconds": 120964.87315,
          "freshness_limit_seconds": 21600.0,
          "latest_utc": "2026-04-17T17:00:00+00:00",
          "retrieved_at_utc": "2026-04-19T02:36:04Z"
        }
      }
    },
    "XAGUSD": {
      "timeframes": {
        "k1m": {
          "provider": "twelvedata",
          "latency_seconds": 89.300471,
          "freshness_limit_seconds": 240.0,
          "latest_utc": "2026-04-19T02:35:00+00:00",
          "retrieved_at_utc": "2026-04-19T02:36:29Z"
        },
        "k5m": {
          "provider": "twelvedata",
          "latency_seconds": 100.219115,
          "freshness_limit_seconds": 900.0,
          "latest_utc": "2026-04-19T02:35:00+00:00",
          "retrieved_at_utc": "2026-04-19T02:36:40Z"
        },
        "k1h": {
          "provider": "twelvedata",
          "latency_seconds": 2182.051019,
          "freshness_limit_seconds": 5400.0,
          "latest_utc": "2026-04-19T02:00:00+00:00",
          "retrieved_at_utc": "2026-04-19T02:36:22Z"
        },
        "k4h": {
          "provider": "twelvedata",
          "latency_seconds": 5780.706312,
          "freshness_limit_seconds": 21600.0,
          "latest_utc": "2026-04-19T01:00:00+00:00",
          "retrieved_at_utc": "2026-04-19T02:36:20Z"
        }
      }
    }
  },
  "providers": {
    "twelvedata": {
      "count": 20,
      "latency_avg_seconds": 24070.728,
      "latency_max_seconds": 120964.87315,
      "stale_count": 4
    },
    "unknown": {
      "count": 4,
      "latency_avg_seconds": null,
      "latency_max_seconds": null,
      "stale_count": 0
    }
  }
}