{
  "generated_utc": "2026-01-04T19:30:28.417212Z",
  "public_dir": "public",
  "assets": {
    "BTCUSD": {
      "timeframes": {
        "k1m": {
          "provider": "twelvedata",
          "latency_seconds": 128.810973,
          "freshness_limit_seconds": 240.0,
          "latest_utc": "2026-01-04T19:28:00+00:00",
          "retrieved_at_utc": "2026-01-04T19:30:08Z"
        },
        "k5m": {
          "provider": "twelvedata",
          "latency_seconds": 303.514425,
          "freshness_limit_seconds": 900.0,
          "latest_utc": "2026-01-04T19:25:00+00:00",
          "retrieved_at_utc": "2026-01-04T19:30:03Z"
        },
        "k1h": {
          "provider": "twelvedata",
          "latency_seconds": 1801.205225,
          "freshness_limit_seconds": 5400.0,
          "latest_utc": "2026-01-04T19:00:00+00:00",
          "retrieved_at_utc": "2026-01-04T19:30:01Z"
        },
        "k4h": {
          "provider": "twelvedata",
          "latency_seconds": 12604.432188,
          "freshness_limit_seconds": 21600.0,
          "latest_utc": "2026-01-04T16:00:00+00:00",
          "retrieved_at_utc": "2026-01-04T19:30:04Z"
        }
      }
    },
    "EURUSD": {
      "timeframes": {
        "k1m": {
          "provider": "twelvedata",
          "latency_seconds": 163833.874978,
          "freshness_limit_seconds": 240.0,
          "latest_utc": "2026-01-02T21:59:00+00:00",
          "retrieved_at_utc": "2026-01-04T19:29:33Z"
        },
        "k5m": {
          "provider": "twelvedata",
          "latency_seconds": 164074.98656,
          "freshness_limit_seconds": 900.0,
          "latest_utc": "2026-01-02T21:55:00+00:00",
          "retrieved_at_utc": "2026-01-04T19:29:34Z"
        },
        "k1h": {
          "provider": "twelvedata",
          "latency_seconds": 167381.501468,
          "freshness_limit_seconds": 5400.0,
          "latest_utc": "2026-01-02T21:00:00+00:00",
          "retrieved_at_utc": "2026-01-04T19:29:41Z"
        },
        "k4h": {
          "provider": "twelvedata",
          "latency_seconds": 170992.500244,
          "freshness_limit_seconds": 21600.0,
          "latest_utc": "2026-01-02T20:00:00+00:00",
          "retrieved_at_utc": "2026-01-04T19:29:52Z"
        }
      }
    },
    "GOLD_CFD": {
      "timeframes": {
        "k1m": {
          "provider": "twelvedata",
          "latency_seconds": 124.073787,
          "freshness_limit_seconds": 240.0,
          "latest_utc": "2026-01-04T19:28:00+00:00",
          "retrieved_at_utc": "2026-01-04T19:30:04Z"
        },
        "k5m": {
          "provider": "twelvedata",
          "latency_seconds": 309.88166,
          "freshness_limit_seconds": 900.0,
          "latest_utc": "2026-01-04T19:25:00+00:00",
          "retrieved_at_utc": "2026-01-04T19:30:09Z"
        },
        "k1h": {
          "provider": "twelvedata",
          "latency_seconds": 1807.686246,
          "freshness_limit_seconds": 5400.0,
          "latest_utc": "2026-01-04T19:00:00+00:00",
          "retrieved_at_utc": "2026-01-04T19:30:07Z"
        },
        "k4h": {
          "provider": "twelvedata",
          "latency_seconds": 12606.617514,
          "freshness_limit_seconds": 21600.0,
          "latest_utc": "2026-01-04T16:00:00+00:00",
          "retrieved_at_utc": "2026-01-04T19:30:06Z"
        }
      }
    },
    "NVDA": {
      "timeframes": {
        "k1m": {
          "provider": "unknown",
          "latency_seconds": null,
          "freshness_limit_seconds": 240.0,
          "latest_utc": null,
          "retrieved_at_utc": "2026-01-04T19:29:09Z"
        },
        "k5m": {
          "provider": "unknown",
          "latency_seconds": null,
          "freshness_limit_seconds": 900.0,
          "latest_utc": null,
          "retrieved_at_utc": "2026-01-04T19:29:09Z"
        },
        "k1h": {
          "provider": "unknown",
          "latency_seconds": null,
          "freshness_limit_seconds": 5400.0,
          "latest_utc": null,
          "retrieved_at_utc": "2026-01-04T19:29:09Z"
        },
        "k4h": {
          "provider": "unknown",
          "latency_seconds": null,
          "freshness_limit_seconds": 21600.0,
          "latest_utc": null,
          "retrieved_at_utc": "2026-01-04T19:29:09Z"
        }
      }
    },
    "USOIL": {
      "timeframes": {
        "k1m": {
          "provider": "twelvedata",
          "latency_seconds": 163828.606014,
          "freshness_limit_seconds": 240.0,
          "latest_utc": "2026-01-02T21:59:00+00:00",
          "retrieved_at_utc": "2026-01-04T19:29:28Z"
        },
        "k5m": {
          "provider": "twelvedata",
          "latency_seconds": 164072.068005,
          "freshness_limit_seconds": 900.0,
          "latest_utc": "2026-01-02T21:55:00+00:00",
          "retrieved_at_utc": "2026-01-04T19:29:32Z"
        },
        "k1h": {
          "provider": "twelvedata",
          "latency_seconds": 167370.949614,
          "freshness_limit_seconds": 5400.0,
          "latest_utc": "2026-01-02T21:00:00+00:00",
          "retrieved_at_utc": "2026-01-04T19:29:30Z"
        },
        "k4h": {
          "provider": "twelvedata",
          "latency_seconds": 170962.553774,
          "freshness_limit_seconds": 21600.0,
          "latest_utc": "2026-01-02T20:00:00+00:00",
          "retrieved_at_utc": "2026-01-04T19:29:22Z"
        }
      }
    },
    "XAGUSD": {
      "timeframes": {
        "k1m": {
          "provider": "twelvedata",
          "latency_seconds": 90.544471,
          "freshness_limit_seconds": 240.0,
          "latest_utc": "2026-01-04T19:28:00+00:00",
          "retrieved_at_utc": "2026-01-04T19:29:30Z"
        },
        "k5m": {
          "provider": "twelvedata",
          "latency_seconds": 266.674648,
          "freshness_limit_seconds": 900.0,
          "latest_utc": "2026-01-04T19:25:00+00:00",
          "retrieved_at_utc": "2026-01-04T19:29:26Z"
        },
        "k1h": {
          "provider": "twelvedata",
          "latency_seconds": 1764.272725,
          "freshness_limit_seconds": 5400.0,
          "latest_utc": "2026-01-04T19:00:00+00:00",
          "retrieved_at_utc": "2026-01-04T19:29:24Z"
        },
        "k4h": {
          "provider": "twelvedata",
          "latency_seconds": 12569.452863,
          "freshness_limit_seconds": 21600.0,
          "latest_utc": "2026-01-04T16:00:00+00:00",
          "retrieved_at_utc": "2026-01-04T19:29:29Z"
        }
      }
    }
  },
  "providers": {
    "twelvedata": {
      "count": 20,
      "latency_avg_seconds": 68844.71,
      "latency_max_seconds": 170992.500244,
      "stale_count": 8
    },
    "unknown": {
      "count": 4,
      "latency_avg_seconds": null,
      "latency_max_seconds": null,
      "stale_count": 0
    }
  }
}