{
  "run": {
    "run_id": "24465636719",
    "captured_at_utc": "2026-04-15T16:21:44Z",
    "started_at_utc": "2026-04-15T16:21:44Z"
  },
  "trading": {
    "started_utc": "2026-04-15T16:21:10Z",
    "completed_utc": "2026-04-15T16:21:40Z",
    "duration_seconds": 29.656
  },
  "updated_utc": "2026-04-15T16:21:44Z",
  "localized_times": {
    "timezone": "Europe/Budapest",
    "run": {
      "captured_at_local": "2026-04-15T18:21:44+02:00",
      "started_at_local": "2026-04-15T18:21:44+02:00"
    },
    "trading": {
      "started_local": "2026-04-15T18:21:10+02:00",
      "completed_local": "2026-04-15T18:21:40+02:00"
    },
    "analysis": {
      "started_local": "2026-04-15T18:21:43+02:00",
      "completed_local": "2026-04-15T18:21:44+02:00"
    },
    "updated_local": "2026-04-15T18:21:44+02:00"
  },
  "execution_order": {
    "analysis_started_utc": "2026-04-15T16:21:43Z",
    "trading_completed_utc": "2026-04-15T16:21:40Z",
    "analysis_after_trading": true
  },
  "analysis": {
    "started_utc": "2026-04-15T16:21:43Z",
    "lag_from_trading_seconds": 3.0,
    "lag_threshold_seconds": 800.0,
    "lag_breached": false,
    "completed_utc": "2026-04-15T16:21:44Z",
    "duration_seconds": 1.237
  },
  "ml_models": {
    "status": {
      "missing": [],
      "placeholders": [],
      "updated_utc": "2026-04-15T16:21:43Z"
    },
    "reminder_period_days": 7
  },
  "artifacts": {
    "hashes": {
      "public/analysis_summary.json": {
        "sha256": "b223f439d5251585a155de71292617d313d2670be029becea9d6e4817a4a9aa9",
        "size": 279422
      },
      "public/status.json": {
        "sha256": "bcf0eba001031957f5b9bf054f68b203b7b7d3dc8e984130279eb9ce29e05d35",
        "size": 533
      },
      "public/monitoring/pipeline_timing.json": {
        "sha256": "0f00f18ec9a35374ce43a15e1c972309945658ebd76d9fd82b70b57b081ba687",
        "size": 1948
      }
    },
    "updated_utc": "2026-04-15T16:21:44Z"
  }
}