{
  "run": {
    "run_id": "24680159466",
    "captured_at_utc": "2026-04-20T17:17:03Z",
    "started_at_utc": "2026-04-20T17:17:03Z"
  },
  "trading": {
    "started_utc": "2026-04-20T17:16:29Z",
    "completed_utc": "2026-04-20T17:16:58Z",
    "duration_seconds": 29.662
  },
  "updated_utc": "2026-04-20T17:17:03Z",
  "localized_times": {
    "timezone": "Europe/Budapest",
    "run": {
      "captured_at_local": "2026-04-20T19:17:03+02:00",
      "started_at_local": "2026-04-20T19:17:03+02:00"
    },
    "trading": {
      "started_local": "2026-04-20T19:16:29+02:00",
      "completed_local": "2026-04-20T19:16:58+02:00"
    },
    "analysis": {
      "started_local": "2026-04-20T19:17:01+02:00",
      "completed_local": "2026-04-20T19:17:03+02:00"
    },
    "updated_local": "2026-04-20T19:17:03+02:00"
  },
  "execution_order": {
    "analysis_started_utc": "2026-04-20T17:17:01Z",
    "trading_completed_utc": "2026-04-20T17:16:58Z",
    "analysis_after_trading": true
  },
  "analysis": {
    "started_utc": "2026-04-20T17:17:01Z",
    "lag_from_trading_seconds": 3.0,
    "lag_threshold_seconds": 800.0,
    "lag_breached": false,
    "completed_utc": "2026-04-20T17:17:03Z",
    "duration_seconds": 1.181
  },
  "ml_models": {
    "status": {
      "missing": [],
      "placeholders": [],
      "updated_utc": "2026-04-20T17:17:02Z"
    },
    "reminder_period_days": 7
  },
  "artifacts": {
    "hashes": {
      "public/analysis_summary.json": {
        "sha256": "23645c9bdb332dcb816c0fa54df005b98de050dfabec4738782b188bfb6843ad",
        "size": 271773
      },
      "public/status.json": {
        "sha256": "c06551f32e809039a759ce6902b5c716549c45611829ff21a9a08cd14d8f1f68",
        "size": 512
      },
      "public/monitoring/pipeline_timing.json": {
        "sha256": "45cdbfdd143f49d0a51f77e6d2fe5fe258ec53cb13f8a04b1fdb5243196c4517",
        "size": 1948
      }
    },
    "updated_utc": "2026-04-20T17:17:03Z"
  }
}