{
  "run": {
    "run_id": "23399446436",
    "captured_at_utc": "2026-03-22T08:46:40Z",
    "started_at_utc": "2026-03-22T08:46:40Z"
  },
  "trading": {
    "started_utc": "2026-03-22T08:45:52Z",
    "completed_utc": "2026-03-22T08:46:36Z",
    "duration_seconds": 43.894
  },
  "updated_utc": "2026-03-22T08:46:40Z",
  "localized_times": {
    "timezone": "Europe/Budapest",
    "run": {
      "captured_at_local": "2026-03-22T09:46:40+01:00",
      "started_at_local": "2026-03-22T09:46:40+01:00"
    },
    "trading": {
      "started_local": "2026-03-22T09:45:52+01:00",
      "completed_local": "2026-03-22T09:46:36+01:00"
    },
    "analysis": {
      "started_local": "2026-03-22T09:46:39+01:00",
      "completed_local": "2026-03-22T09:46:40+01:00"
    },
    "updated_local": "2026-03-22T09:46:40+01:00"
  },
  "execution_order": {
    "analysis_started_utc": "2026-03-22T08:46:39Z",
    "trading_completed_utc": "2026-03-22T08:46:36Z",
    "analysis_after_trading": true
  },
  "analysis": {
    "started_utc": "2026-03-22T08:46:39Z",
    "lag_from_trading_seconds": 3.0,
    "lag_threshold_seconds": 800.0,
    "lag_breached": false,
    "completed_utc": "2026-03-22T08:46:40Z",
    "duration_seconds": 0.862
  },
  "ml_models": {
    "status": {
      "missing": [],
      "placeholders": [],
      "updated_utc": "2026-03-22T08:46:39Z"
    },
    "reminder_period_days": 7
  },
  "artifacts": {
    "hashes": {
      "public/analysis_summary.json": {
        "sha256": "b8f075562710127f21e28c70bd6d56460a17cd20b8134593459c4873694759c0",
        "size": 196451
      },
      "public/status.json": {
        "sha256": "82804fa45333c69163b9bbf985d11ab8bb5d2045a5b1d8031726f7ca71e9b7a1",
        "size": 635
      },
      "public/monitoring/pipeline_timing.json": {
        "sha256": "21ec1ebb02b8381264aeb019eac7745f90cf664a8318be8858b15f8ed7a74c34",
        "size": 1948
      }
    },
    "updated_utc": "2026-03-22T08:46:40Z"
  }
}