{
  "run": {
    "run_id": "23129504310",
    "captured_at_utc": "2026-03-16T05:37:59Z",
    "started_at_utc": "2026-03-16T05:37:59Z"
  },
  "trading": {
    "started_utc": "2026-03-16T05:36:22Z",
    "completed_utc": "2026-03-16T05:36:39Z",
    "duration_seconds": 17.443
  },
  "updated_utc": "2026-03-16T05:37:59Z",
  "localized_times": {
    "timezone": "Europe/Budapest",
    "run": {
      "captured_at_local": "2026-03-16T06:37:59+01:00",
      "started_at_local": "2026-03-16T06:37:59+01:00"
    },
    "trading": {
      "started_local": "2026-03-16T06:36:22+01:00",
      "completed_local": "2026-03-16T06:36:39+01:00"
    },
    "analysis": {
      "started_local": "2026-03-16T06:37:58+01:00",
      "completed_local": "2026-03-16T06:37:59+01:00"
    },
    "updated_local": "2026-03-16T06:37:59+01:00"
  },
  "execution_order": {
    "analysis_started_utc": "2026-03-16T05:37:58Z",
    "trading_completed_utc": "2026-03-16T05:36:39Z",
    "analysis_after_trading": true
  },
  "analysis": {
    "started_utc": "2026-03-16T05:37:58Z",
    "lag_from_trading_seconds": 79.0,
    "lag_threshold_seconds": 240.0,
    "lag_breached": false,
    "completed_utc": "2026-03-16T05:37:59Z",
    "duration_seconds": 1.039
  },
  "ml_models": {
    "status": {
      "missing": [],
      "placeholders": [],
      "updated_utc": "2026-03-16T05:37:58Z"
    },
    "reminder_period_days": 7
  },
  "artifacts": {
    "hashes": {
      "public/analysis_summary.json": {
        "sha256": "d0c5e0bd8c0d61694d82a5fc4e97caa77ac541e6dcce45227c37134562913c13",
        "size": 247718
      },
      "public/status.json": {
        "sha256": "006709f77e629af8d67c2fa6d8d52bc251aff2f3b8f303abe547a1404ebcfd80",
        "size": 547
      },
      "public/monitoring/pipeline_timing.json": {
        "sha256": "f303d7fe05dab6dabfaba1db127ea05a0584d34cca58adfa84943bfffb33bdd5",
        "size": 1949
      }
    },
    "updated_utc": "2026-03-16T05:37:59Z"
  }
}