{
  "run": {
    "run_id": "26257503620",
    "captured_at_utc": "2026-05-21T22:47:01Z",
    "started_at_utc": "2026-05-21T22:47:01Z"
  },
  "trading": {
    "started_utc": "2026-05-21T22:46:33Z",
    "completed_utc": "2026-05-21T22:46:57Z",
    "duration_seconds": 24.129
  },
  "updated_utc": "2026-05-21T22:47:01Z",
  "localized_times": {
    "timezone": "Europe/Budapest",
    "run": {
      "captured_at_local": "2026-05-22T00:47:01+02:00",
      "started_at_local": "2026-05-22T00:47:01+02:00"
    },
    "trading": {
      "started_local": "2026-05-22T00:46:33+02:00",
      "completed_local": "2026-05-22T00:46:57+02:00"
    },
    "analysis": {
      "started_local": "2026-05-22T00:47:00+02:00",
      "completed_local": "2026-05-22T00:47:01+02:00"
    },
    "updated_local": "2026-05-22T00:47:01+02:00"
  },
  "execution_order": {
    "analysis_started_utc": "2026-05-21T22:47:00Z",
    "trading_completed_utc": "2026-05-21T22:46:57Z",
    "analysis_after_trading": true
  },
  "analysis": {
    "started_utc": "2026-05-21T22:47:00Z",
    "lag_from_trading_seconds": 3.0,
    "lag_threshold_seconds": 800.0,
    "lag_breached": false,
    "completed_utc": "2026-05-21T22:47:01Z",
    "duration_seconds": 0.982
  },
  "ml_models": {
    "status": {
      "missing": [],
      "placeholders": [],
      "updated_utc": "2026-05-21T22:47:00Z"
    },
    "reminder_period_days": 7
  },
  "artifacts": {
    "hashes": {
      "public/analysis_summary.json": {
        "sha256": "49eeadd469ab1e4b9448c6b48b9d82c714aac5e56029c1fb09e8cc1a3c11c155",
        "size": 209299
      },
      "public/status.json": {
        "sha256": "dd0c24f648bec4590207b26ac695b9b1d341001466dd0d7a21d50e6d775cf964",
        "size": 538
      },
      "public/monitoring/pipeline_timing.json": {
        "sha256": "0c8f7428db91e06fae8d94cfffb9193d210d3c931c4f1dcb6c65aec88590f2ad",
        "size": 1948
      }
    },
    "updated_utc": "2026-05-21T22:47:01Z"
  }
}